torchdr/__about__.py
torchdr/__init__.py
torchdr/affinity_matcher.py
torchdr/base.py
torchdr/clustering.py
torchdr/eval.py
torchdr/affinity/__init__.py
torchdr/affinity/base.py
torchdr/affinity/entropic.py
torchdr/affinity/knn_normalized.py
torchdr/affinity/quadratic.py
torchdr/affinity/unnormalized.py
torchdr/distance/__init__.py
torchdr/distance/base.py
torchdr/distance/faiss.py
torchdr/distance/keops.py
torchdr/distance/torch.py
torchdr/neighbor_embedding/__init__.py
torchdr/neighbor_embedding/base.py
torchdr/neighbor_embedding/cosne.py
torchdr/neighbor_embedding/infotsne.py
torchdr/neighbor_embedding/largevis.py
torchdr/neighbor_embedding/pacmap.py
torchdr/neighbor_embedding/sne.py
torchdr/neighbor_embedding/tsne.py
torchdr/neighbor_embedding/tsnekhorn.py
torchdr/neighbor_embedding/umap.py
torchdr/spectral_embedding/__init__.py
torchdr/spectral_embedding/incremental_pca.py
torchdr/spectral_embedding/kernel_pca.py
torchdr/spectral_embedding/pca.py
torchdr/spectral_embedding/phate.py
torchdr/tests/conftest.py
torchdr/tests/test_affinity.py
torchdr/tests/test_affinity_matcher.py
torchdr/tests/test_clustering.py
torchdr/tests/test_estimators.py
torchdr/tests/test_eval.py
torchdr/tests/test_incremental_pca.py
torchdr/tests/test_neighbor_embedding.py
torchdr/tests/test_spectral.py
torchdr/tests/test_utils.py
torchdr/tests/test_visu.py
torchdr/tests/utils.py
torchdr/utils/__init__.py
torchdr/utils/faiss.py
torchdr/utils/keops.py
torchdr/utils/manifold.py
torchdr/utils/radam.py
torchdr/utils/root_search.py
torchdr/utils/sparse.py
torchdr/utils/utils.py
torchdr/utils/validation.py
torchdr/utils/visu.py
torchdr/utils/wrappers.py
torchdr-0.3.dist-info/licenses/LICENSE
torchdr-0.3.dist-info/METADATA
torchdr-0.3.dist-info/WHEEL
torchdr-0.3.dist-info/top_level.txt
torchdr-0.3.dist-info/RECORD
