Metadata-Version: 2.4
Name: torchdr
Version: 0.3
Summary: Torch Dimensionality Reduction Library
Author:  TorchDR contributors
Author-email: Hugues Van Assel <vanasselhugues@gmail.com>
License: BSD (3-Clause)
Project-URL: homepage, https://torchdr.github.io/
Project-URL: documentation, https://torchdr.github.io/
Project-URL: repository, https://github.com/TorchDR/TorchDR
Keywords: dimensionality reduction,machine learning,data analysis,pytorch,scikit-learn,GPU
Classifier: Intended Audience :: Science/Research
Classifier: Intended Audience :: Developers
Classifier: License :: OSI Approved :: BSD License
Classifier: Programming Language :: Python
Classifier: Topic :: Software Development
Classifier: Topic :: Scientific/Engineering
Classifier: Development Status :: 3 - Alpha
Classifier: Operating System :: Microsoft :: Windows
Classifier: Operating System :: POSIX
Classifier: Operating System :: Unix
Classifier: Operating System :: MacOS
Classifier: Programming Language :: Python :: 3.7
Classifier: Programming Language :: Python :: 3.8
Classifier: Programming Language :: Python :: 3.9
Classifier: Programming Language :: Python :: 3.10
Classifier: Programming Language :: Python :: 3.11
Classifier: Programming Language :: Python :: 3.12
Requires-Python: >=3.7
License-File: LICENSE
Requires-Dist: torch
Requires-Dist: scikit-learn
Requires-Dist: numpy
Provides-Extra: test
Requires-Dist: pytest; extra == "test"
Requires-Dist: flake8; extra == "test"
Requires-Dist: coverage; extra == "test"
Requires-Dist: numpydoc; extra == "test"
Requires-Dist: pytest-cov; extra == "test"
Requires-Dist: codecov; extra == "test"
Requires-Dist: matplotlib; extra == "test"
Provides-Extra: keops
Requires-Dist: pykeops; extra == "keops"
Provides-Extra: dev
Requires-Dist: pytest; extra == "dev"
Requires-Dist: coverage; extra == "dev"
Requires-Dist: numpydoc; extra == "dev"
Requires-Dist: pytest-cov; extra == "dev"
Requires-Dist: codecov; extra == "dev"
Requires-Dist: pykeops; extra == "dev"
Requires-Dist: pre-commit; extra == "dev"
Provides-Extra: doc
Requires-Dist: sphinx; extra == "doc"
Requires-Dist: sphinx_gallery; extra == "doc"
Requires-Dist: pydata_sphinx_theme; extra == "doc"
Requires-Dist: sphinxcontrib-bibtex; extra == "doc"
Requires-Dist: matplotlib; extra == "doc"
Requires-Dist: numpydoc; extra == "doc"
Requires-Dist: memory_profiler; extra == "doc"
Requires-Dist: myst-parser; extra == "doc"
Requires-Dist: pandas; extra == "doc"
Provides-Extra: examples
Requires-Dist: matplotlib; extra == "examples"
Requires-Dist: seaborn; extra == "examples"
Requires-Dist: pandas; extra == "examples"
Requires-Dist: transformers; extra == "examples"
Requires-Dist: datasets; extra == "examples"
Requires-Dist: datamapplot; extra == "examples"
Provides-Extra: benchmarks
Requires-Dist: psutil; extra == "benchmarks"
Requires-Dist: requests; extra == "benchmarks"
Requires-Dist: umap-learn; extra == "benchmarks"
Provides-Extra: all
Requires-Dist: torchdr[benchmarks,dev,doc,examples,keops,test]; extra == "all"
Dynamic: license-file
